empty_trashcan/__init__.py
empty_trashcan/empty.py
empty_trashcan/trashcan.py
emptytrashcan/__init__.py
emptytrashcan/trashcan.py
emptytrashcan-0.0.3.dist-info/LICENSE
emptytrashcan-0.0.3.dist-info/METADATA
emptytrashcan-0.0.3.dist-info/WHEEL
emptytrashcan-0.0.3.dist-info/top_level.txt
emptytrashcan-0.0.3.dist-info/RECORD
